Metadata-Version: 1.0
Name: dsnd-distributions-anchelus
Version: 1.0
Summary: Gaussian and Binomial distributions
Home-page: UNKNOWN
Author: Kevin Darmasaputra
Author-email: kevin@azurebaycapital.com
License: UNKNOWN
Platform: UNKNOWN
